core/__init__.py
core/analyseur.py
core/simulateur.py
data/__init__.py
models/__init__.py
models/reseau.py
models/route.py
models/vehicule.py
ui/__init__.py
ui/affichage.py
ui/export.py
simulateur_trafic_omar_kassar-0.1.0.dist-info/METADATA
simulateur_trafic_omar_kassar-0.1.0.dist-info/WHEEL
simulateur_trafic_omar_kassar-0.1.0.dist-info/entry_points.txt
simulateur_trafic_omar_kassar-0.1.0.dist-info/top_level.txt
simulateur_trafic_omar_kassar-0.1.0.dist-info/RECORD
