Metadata-Version: 2.4
Name: simulateur-trafic-omar-kassar
Version: 0.1.0
Summary: Simulateur modulaire de réseau routier intelligent
Author-email: Omar Kassar <omarkassar202@gmail.com>
Requires-Python: >=3.9
Requires-Dist: matplotlib
Requires-Dist: pandas
